{"data":{"Year":[2015,2016,2017,2018,2019,2020,2021,2022,2023,2015,2016,2017,2018,2019,2020,2021,2022,2023,2015,2016,2017,2018,2019,2020,2021,2022,2023,2015,2016,2017,2018,2019,2020,2021,2022,2023,2015,2016,2017,2018,2019,2020,2021,2022,2023],"Mean_of_transportation":["A peu","A peu","A peu","A peu","A peu","A peu","A peu","A peu","A peu","Transport privat motoritzat","Transport privat motoritzat","Transport privat motoritzat","Transport privat motoritzat","Transport privat motoritzat","Transport privat motoritzat","Transport privat motoritzat","Transport privat motoritzat","Transport privat motoritzat","Bicicleta i VMP","Bicicleta i VMP","Bicicleta i VMP","Bicicleta i VMP","Bicicleta i VMP","Bicicleta i VMP","Bicicleta i VMP","Bicicleta i VMP","Bicicleta i VMP","Transport public","Transport public","Transport public","Transport public","Transport public","Transport public","Transport public","Transport public","Transport public","Ecomobilitat","Ecomobilitat","Ecomobilitat","Ecomobilitat","Ecomobilitat","Ecomobilitat","Ecomobilitat","Ecomobilitat","Ecomobilitat"],"Units":["Percentatge","Percentatge","Percentatge","Percentatge","Percentatge","Percentatge","Percentatge","Percentatge","Percentatge","Percentatge","Percentatge","Percentatge","Percentatge","Percentatge","Percentatge","Percentatge","Percentatge","Percentatge","Percentatge","Percentatge","Percentatge","Percentatge","Percentatge","Percentatge","Percentatge","Percentatge","Percentatge","Percentatge","Percentatge","Percentatge","Percentatge","Percentatge","Percentatge","Percentatge","Percentatge","Percentatge","Percentatge","Percentatge","Percentatge","Percentatge","Percentatge","Percentatge","Percentatge","Percentatge","Percentatge"],"Value":[43.5,35.6,34.5,40.1,42.5,48.8,45.5,44.0,42.1,20.6,22.9,22.3,21.4,20.1,21.5,23.5,21.3,19.9,1.6,2.2,2.6,2.5,2.7,3.5,3.2,3.8,3.8,34.2,39.2,40.6,36.0,34.7,26.1,27.8,30.9,34.2,79.4,77.1,77.7,78.6,79.9,78.5,76.5,78.7,80.1]},"edges":[]}